forca2/main.py
forca2/jogo/__init__.py
forca2/jogo/jogo.py
forca2/menu/__init__.py
forca2/menu/menu.py
forca2/titulo/__init__.py
forca2/titulo/titulo.py
forca2/utils/__init__.py
forca2/utils/bancodepalavras.py
forca2/utils/utilidades.py
forca2-0.1.2.dist-info/licenses/LICENSE.txt
forca2-0.1.2.dist-info/METADATA
forca2-0.1.2.dist-info/WHEEL
forca2-0.1.2.dist-info/entry_points.txt
forca2-0.1.2.dist-info/top_level.txt
forca2-0.1.2.dist-info/RECORD
