Metadata-Version: 2.4
Name: forca2
Version: 0.1.2
Summary: Forca 2.0 é uma versão moderna e divertida do clássico jogo da forca, jogado diretamente no terminal.
Author-email: Lucas Rodrigues Mendonça <lucas80002@gmail.com>
License: MIT
Project-URL: Homepage, https://github.com/lucasrmendonca7/forca-2.0-ascii
Project-URL: Bug Tracker, https://github.com/lucasrmendonca7/forca-2.0-ascii/issues
Requires-Python: >=3.8
License-File: LICENSE.txt
Dynamic: license-file
